django_settings_inspector/__init__.py
django_settings_inspector/__version__.py
django_settings_inspector/base.py
django_settings_inspector/cli.py
django_settings_inspector/management/commands/__init__.py
django_settings_inspector/management/commands/all.py
django_settings_inspector/management/commands/auth.py
django_settings_inspector/management/commands/cache.py
django_settings_inspector/management/commands/core.py
django_settings_inspector/management/commands/db.py
django_settings_inspector/management/commands/diffsettings.py
django_settings_inspector/management/commands/email.py
django_settings_inspector/management/commands/installed.py
django_settings_inspector/management/commands/locale.py
django_settings_inspector/management/commands/logging.py
django_settings_inspector/management/commands/media.py
django_settings_inspector/management/commands/middleware.py
django_settings_inspector/management/commands/security.py
django_settings_inspector/management/commands/session.py
django_settings_inspector/management/commands/site.py
django_settings_inspector/management/commands/static.py
django_settings_inspector/management/commands/storage.py
django_settings_inspector/management/commands/template.py
django_settings_inspector/management/commands/validator.py
django_settings_inspector-1.0.5.dist-info/licenses/LICENSE
django_settings_inspector-1.0.5.dist-info/METADATA
django_settings_inspector-1.0.5.dist-info/WHEEL
django_settings_inspector-1.0.5.dist-info/entry_points.txt
django_settings_inspector-1.0.5.dist-info/top_level.txt
django_settings_inspector-1.0.5.dist-info/RECORD
