Metadata-Version: 2.4
Name: django_settings_inspector
Version: 1.0.5
Summary: A Django management and CLI tool to inspect and colorize project settings
Home-page: https://github.com/cumulus13/django-settings-inspector
Author: Hadi Cahyadi
Author-email: cumulus13@gmail.com
License: MIT
Classifier: Framework :: Django
Classifier: Programming Language :: Python :: 3
Classifier: License :: OSI Approved :: MIT License
Classifier: Operating System :: OS Independent
Classifier: Environment :: Console
License-File: LICENSE
Requires-Dist: Django>=3.2
Requires-Dist: rich>=13.0
Dynamic: author
Dynamic: author-email
Dynamic: classifier
Dynamic: description
Dynamic: description-content-type
Dynamic: home-page
Dynamic: license
Dynamic: license-file
Dynamic: requires-dist
Dynamic: summary
